sourcerer/__init__.py
sourcerer/settings.py
sourcerer/utils.py
sourcerer/domain/__init__.py
sourcerer/domain/access_credentials/__init__.py
sourcerer/domain/access_credentials/entities.py
sourcerer/domain/access_credentials/exceptions.py
sourcerer/domain/access_credentials/repositories.py
sourcerer/domain/access_credentials/services.py
sourcerer/domain/file_system/__init__.py
sourcerer/domain/file_system/entities.py
sourcerer/domain/file_system/exceptions.py
sourcerer/domain/file_system/services.py
sourcerer/domain/package_meta/__init__.py
sourcerer/domain/package_meta/entities.py
sourcerer/domain/package_meta/services.py
sourcerer/domain/settings/__init__.py
sourcerer/domain/settings/entities.py
sourcerer/domain/settings/repositories.py
sourcerer/domain/settings/services.py
sourcerer/domain/shared/__init__.py
sourcerer/domain/shared/entities.py
sourcerer/domain/storage/__init__.py
sourcerer/domain/storage/entities.py
sourcerer/domain/storage/repositories.py
sourcerer/domain/storage_provider/__init__.py
sourcerer/domain/storage_provider/entities.py
sourcerer/domain/storage_provider/exceptions.py
sourcerer/domain/storage_provider/services.py
sourcerer/infrastructure/__init__.py
sourcerer/infrastructure/utils.py
sourcerer/infrastructure/access_credentials/__init__.py
sourcerer/infrastructure/access_credentials/exceptions.py
sourcerer/infrastructure/access_credentials/registry.py
sourcerer/infrastructure/access_credentials/repositories.py
sourcerer/infrastructure/access_credentials/services.py
sourcerer/infrastructure/db/__init__.py
sourcerer/infrastructure/db/config.py
sourcerer/infrastructure/db/models.py
sourcerer/infrastructure/file_system/__init__.py
sourcerer/infrastructure/file_system/exceptions.py
sourcerer/infrastructure/file_system/services.py
sourcerer/infrastructure/package_meta/__init__.py
sourcerer/infrastructure/package_meta/services.py
sourcerer/infrastructure/settings/__init__.py
sourcerer/infrastructure/settings/repositories.py
data_sourcerer-0.8.1.dist-info/METADATA
data_sourcerer-0.8.1.dist-info/WHEEL
data_sourcerer-0.8.1.dist-info/entry_points.txt
data_sourcerer-0.8.1.dist-info/licenses/LICENSE
data_sourcerer-0.8.1.dist-info/RECORD
